<package>
  <description brief="nao_demo">

    Nao demo components for BARC.

  </description>
  <author>Nick Hawes</author>
  <license>BSD</license>
  <review status="unreviewed" notes=""/>
  <url>http://ros.org/wiki/nao_demo</url>
  <depend package="nao_teleop"/>
  <depend package="nao_driver"/>
  <depend package="nao_remote"/>
  <depend package="nao_components"/>
  <depend package="nao_msgs"/>  
  <depend package="joy"/>
  <depend package="std_srvs"/>
  <depend package="actionlib"/>


</package>


